{
  "collection_name": "tickets",
  "export_timestamp": "2025-07-30T10:54:45.320072",
  "total_documents": 210,
  "data": [
    {
      "_id": "ticket1",
      "booking_id": "booking1",
      "seat_id": "hn_hall1_A1",
      "status": "checked_in",
      "checkin_time": null,
      "checked_by": null,
      "qr_code": "QR_HN_A1",
      "barcode_data": "STEUT9n1A120250715",
      "checked_in_at": "2025-07-29T19:05:55.097000",
      "checked_in_by": "staff"
    },
    {
      "_id": "ticket2",
      "booking_id": "booking1",
      "seat_id": "hn_hall1_A2",
      "status": "checked_in",
      "checkin_time": null,
      "checked_by": null,
      "qr_code": "QR_HN_A2",
      "barcode_data": "ST0EH0n1A220250715",
      "checked_in_at": "2025-07-29T19:06:23.025000",
      "checked_in_by": "staff"
    },
    {
      "_id": "ticket3",
      "booking_id": "booking2",
      "seat_id": "sg_hall1_A1",
      "status": "checked_in",
      "checkin_time": null,
      "checked_by": null,
      "qr_code": "QR_SG_A1",
      "barcode_data": "STNATBg1A120250715",
      "checked_in_at": "2025-07-29T19:06:23.026000",
      "checked_in_by": "staff"
    },
    {
      "_id": "ticket4",
      "booking_id": "booking2",
      "seat_id": "sg_hall1_A2",
      "status": "confirmed",
      "checkin_time": null,
      "checked_by": null,
      "qr_code": "QR_SG_A2",
      "barcode_data": "STG25Qg1A220250715"
    },
    {
      "_id": "6875b16fa09073c0b442546c",
      "booking_id": "bk6875b1",
      "seat_id": "sg_hall2_A6",
      "status": "confirmed",
      "qr_code": "QR6875b16f",
      "barcode_data": "STW1YXg2A620250715"
    },
    {
      "_id": "6875b16fa09073c0b442546e",
      "booking_id": "bk6875b1",
      "seat_id": "sg_hall2_B6",
      "status": "confirmed",
      "qr_code": "QR6875b16f",
      "barcode_data": "STGCN0g2B620250715"
    },
    {
      "_id": "6875ba0fa09073c0b4425472",
      "booking_id": "bk6875ba",
      "seat_id": "sg_hall2_A7",
      "status": "confirmed",
      "qr_code": "QR6875ba0f",
      "barcode_data": "ST0JG2g2A720250715"
    },
    {
      "_id": "6875ba0fa09073c0b4425474",
      "booking_id": "bk6875ba",
      "seat_id": "sg_hall2_A8",
      "status": "confirmed",
      "qr_code": "QR6875ba0f",
      "barcode_data": "STX5UHg2A820250715"
    },
    {
      "_id": "6875d2f0b7972be1053ced47",
      "booking_id": "bk6875d2",
      "seat_id": "sg_hall2_A9",
      "status": "cancelled",
      "checkin_time": null,
      "checked_by": null,
      "barcode_data": "STHTTYA9220250715",
      "created_at": "2025-07-15T04:02:56.503000",
      "cancelled_at": "2025-07-15T09:21:34.527000"
    },
    {
      "_id": "6875d37fb7972be1053ced49",
      "booking_id": "bk6875d3",
      "seat_id": "sg_hall2_A10",
      "status": "cancelled",
      "checkin_time": null,
      "checked_by": null,
      "barcode_data": "STHTTYA10220250715",
      "created_at": "2025-07-15T04:05:19.025000",
      "cancelled_at": "2025-07-15T09:21:34.558000"
    },
    {
      "_id": "6875d37fb7972be1053ced4a",
      "booking_id": "bk6875d3",
      "seat_id": "sg_hall2_B10",
      "status": "cancelled",
      "checkin_time": null,
      "checked_by": null,
      "barcode_data": "STHTTYB10220250715",
      "created_at": "2025-07-15T04:05:19.026000",
      "cancelled_at": "2025-07-15T09:21:34.558000"
    },
    {
      "_id": "6875d5abb7972be1053ced4c",
      "booking_id": "bk6875d5",
      "seat_id": "sg_hall2_A7",
      "status": "cancelled",
      "checkin_time": null,
      "checked_by": null,
      "barcode_data": "STHTTYA7220250715",
      "created_at": "2025-07-15T04:14:35.930000",
      "cancelled_at": "2025-07-15T09:21:34.560000"
    },
    {
      "_id": "6875d5abb7972be1053ced4d",
      "booking_id": "bk6875d5",
      "seat_id": "sg_hall2_A8",
      "status": "cancelled",
      "checkin_time": null,
      "checked_by": null,
      "barcode_data": "STHTTYA8220250715",
      "created_at": "2025-07-15T04:14:35.931000",
      "cancelled_at": "2025-07-15T09:21:34.560000"
    },
    {
      "_id": "6875dcc8897ec1f3e02f7c56",
      "booking_id": "bk6875dc",
      "seat_id": "sg_hall2_B8",
      "status": "cancelled",
      "checkin_time": null,
      "checked_by": null,
      "barcode_data": "STHTTYB8220250715",
      "created_at": "2025-07-15T04:44:56.997000",
      "cancelled_at": "2025-07-15T09:21:34.561000"
    },
    {
      "_id": "6875dcc8897ec1f3e02f7c57",
      "booking_id": "bk6875dc",
      "seat_id": "sg_hall2_B9",
      "status": "cancelled",
      "checkin_time": null,
      "checked_by": null,
      "barcode_data": "STHTTYB9220250715",
      "created_at": "2025-07-15T04:44:56.997000",
      "cancelled_at": "2025-07-15T09:21:34.561000"
    },
    {
      "_id": "68761a22f9ab698717d2ff09",
      "booking_id": "bk68761a",
      "seat_id": "sg_hall2_A4",
      "status": "cancelled",
      "checkin_time": null,
      "checked_by": null,
      "barcode_data": "STHTTYA4220250715",
      "created_at": "2025-07-15T09:06:42.295000",
      "cancelled_at": "2025-07-15T09:21:34.563000"
    },
    {
      "_id": "68761a22f9ab698717d2ff0a",
      "booking_id": "bk68761a",
      "seat_id": "sg_hall2_B4",
      "status": "cancelled",
      "checkin_time": null,
      "checked_by": null,
      "barcode_data": "STHTTYB4220250715",
      "created_at": "2025-07-15T09:06:42.297000",
      "cancelled_at": "2025-07-15T09:21:34.563000"
    },
    {
      "_id": "68761cd30c65e5320458bb85",
      "booking_id": "bk68761c",
      "seat_id": "sg_hall2_D7",
      "status": "cancelled",
      "checkin_time": null,
      "checked_by": null,
      "barcode_data": "STHTTYD7220250715",
      "created_at": "2025-07-15T09:18:11.067000",
      "cancelled_at": "2025-07-15T09:29:39.861000"
    },
    {
      "_id": "68761cd30c65e5320458bb86",
      "booking_id": "bk68761c",
      "seat_id": "sg_hall2_D8",
      "status": "cancelled",
      "checkin_time": null,
      "checked_by": null,
      "barcode_data": "STHTTYD8220250715",
      "created_at": "2025-07-15T09:18:11.068000",
      "cancelled_at": "2025-07-15T09:29:39.861000"
    },
    {
      "_id": "68761dd119fa95d63d25a2f7",
      "booking_id": "bk68761d",
      "seat_id": "sg_hall2_B7",
      "status": "cancelled",
      "checkin_time": null,
      "checked_by": null,
      "barcode_data": "STHTTYB7220250715",
      "created_at": "2025-07-15T09:22:25.106000",
      "cancelled_at": "2025-07-15T09:35:00.015000"
    },
    {
      "_id": "68761f8819fa95d63d25a2f9",
      "booking_id": "bk68761f",
      "seat_id": "sg_hall2_B8",
      "status": "cancelled",
      "checkin_time": null,
      "checked_by": null,
      "barcode_data": "STHTTYB8220250715",
      "created_at": "2025-07-15T09:29:44.361000",
      "cancelled_at": "2025-07-15T09:39:45.613000"
    },
    {
      "_id": "687620e3c98f4ce23cb3d8af",
      "booking_id": "bk687620",
      "seat_id": "sg_hall2_A7",
      "status": "cancelled",
      "checkin_time": null,
      "checked_by": null,
      "barcode_data": "STHTTYA7220250715",
      "created_at": "2025-07-15T09:35:31.155000",
      "cancelled_at": "2025-07-15T09:48:16.876000"
    },
    {
      "_id": "687621dd34be59031c652607",
      "booking_id": "bk687621",
      "seat_id": "sg_hall2_A8",
      "status": "checked_in",
      "checkin_time": null,
      "checked_by": null,
      "barcode_data": "STHTTYA8220250715",
      "created_at": "2025-07-15T09:39:41.565000",
      "checked_in_at": "2025-07-29T19:27:01.313000",
      "checked_in_by": "staff"
    },
    {
      "_id": "6876229e07787382983409ed",
      "booking_id": "bk6876229e07787382983409ec",
      "seat_id": "sg_hall2_A9",
      "status": "checked_in",
      "checkin_time": null,
      "checked_by": null,
      "barcode_data": "STHTTYA9220250715",
      "created_at": "2025-07-15T09:42:54.197000",
      "checked_in_at": "2025-07-29T19:27:08.214000",
      "checked_in_by": "staff"
    },
    {
      "_id": "687622a707787382983409ef",
      "booking_id": "bk687622a707787382983409ee",
      "seat_id": "sg_hall2_D3",
      "status": "checked_in",
      "checkin_time": null,
      "checked_by": null,
      "barcode_data": "STHTTYD3220250715",
      "created_at": "2025-07-15T09:43:03.400000",
      "checked_in_at": "2025-07-29T19:27:08.215000",
      "checked_in_by": "staff"
    },
    {
      "_id": "687622a707787382983409f0",
      "booking_id": "bk687622a707787382983409ee",
      "seat_id": "sg_hall2_D4",
      "status": "valid",
      "checkin_time": null,
      "checked_by": null,
      "barcode_data": "STHTTYD4220250715",
      "created_at": "2025-07-15T09:43:03.401000"
    },
    {
      "_id": "687623eaa845e46b8a3de688",
      "booking_id": "bk687623eaa845e46b8a3de687",
      "seat_id": "sg_hall2_C7",
      "status": "valid",
      "checkin_time": null,
      "checked_by": null,
      "barcode_data": "STHTTYC7220250715",
      "created_at": "2025-07-15T09:48:26.466000"
    },
    {
      "_id": "6876262c08f178c29f00be8f",
      "booking_id": "bk6876262c08f178c29f00be8e",
      "seat_id": "sg_hall2_A7",
      "status": "valid",
      "checkin_time": null,
      "checked_by": null,
      "barcode_data": "STHTTYA7220250715",
      "created_at": "2025-07-15T09:58:04.364000"
    },
    {
      "_id": "6876262c08f178c29f00be90",
      "booking_id": "bk6876262c08f178c29f00be8e",
      "seat_id": "sg_hall2_A8",
      "status": "valid",
      "checkin_time": null,
      "checked_by": null,
      "barcode_data": "STHTTYA8220250715",
      "created_at": "2025-07-15T09:58:04.365000"
    },
    {
      "_id": "687627ebef04855eda624ab1",
      "booking_id": "bk687627ebef04855eda624ab0",
      "seat_id": "sg_hall2_B8",
      "status": "valid",
      "checkin_time": null,
      "checked_by": null,
      "barcode_data": "STHTTYB8220250715",
      "created_at": "2025-07-15T10:05:31.813000"
    },
    {
      "_id": "687628be2355e4aaa8853e2d",
      "booking_id": "bk687628be2355e4aaa8853e2c",
      "seat_id": "sg_hall2_A1",
      "status": "cancelled",
      "checkin_time": null,
      "checked_by": null,
      "barcode_data": "STHTTYA1220250715",
      "created_at": "2025-07-15T10:09:02.321000",
      "cancelled_at": "2025-07-15T10:14:53.613000"
    },
    {
      "_id": "687628be2355e4aaa8853e2e",
      "booking_id": "bk687628be2355e4aaa8853e2c",
      "seat_id": "sg_hall2_A2",
      "status": "cancelled",
      "checkin_time": null,
      "checked_by": null,
      "barcode_data": "STHTTYA2220250715",
      "created_at": "2025-07-15T10:09:02.322000",
      "cancelled_at": "2025-07-15T10:14:53.613000"
    },
    {
      "_id": "687630f2287847dadfa92a7b",
      "booking_id": "bk687630f2287847dadfa92a7a",
      "seat_id": "sg_hall2_A1",
      "status": "valid",
      "checkin_time": null,
      "checked_by": null,
      "barcode_data": "STHTTYA1220250715",
      "created_at": "2025-07-15T10:44:02.870000"
    },
    {
      "_id": "687633a789beb7c924a1e84b",
      "booking_id": "bk687633a789beb7c924a1e84a",
      "seat_id": "sg_hall2_A2",
      "status": "valid",
      "checkin_time": null,
      "checked_by": null,
      "barcode_data": "STHTTYA2220250715",
      "created_at": "2025-07-15T10:55:35.855000"
    },
    {
      "_id": "687635bc89beb7c924a1e84e",
      "booking_id": "bk687635bc89beb7c924a1e84d",
      "seat_id": "sg_hall2_A3",
      "status": "valid",
      "checkin_time": null,
      "checked_by": null,
      "barcode_data": "STHTTYA3220250715",
      "created_at": "2025-07-15T11:04:28.510000"
    },
    {
      "_id": "687637aeb007408b4f73c6a5",
      "booking_id": "bk687637aeb007408b4f73c6a4",
      "seat_id": "sg_hall2_B5",
      "status": "valid",
      "checkin_time": null,
      "checked_by": null,
      "barcode_data": "STHTTYB5220250715",
      "created_at": "2025-07-15T11:12:46.990000"
    },
    {
      "_id": "68763903b007408b4f73c6a8",
      "booking_id": "bk68763903b007408b4f73c6a7",
      "seat_id": "sg_hall2_A4",
      "status": "valid",
      "checkin_time": null,
      "checked_by": null,
      "barcode_data": "STHTTYA4220250715",
      "created_at": "2025-07-15T11:18:27.587000"
    },
    {
      "_id": "68763903b007408b4f73c6a9",
      "booking_id": "bk68763903b007408b4f73c6a7",
      "seat_id": "sg_hall2_A5",
      "status": "valid",
      "checkin_time": null,
      "checked_by": null,
      "barcode_data": "STHTTYA5220250715",
      "created_at": "2025-07-15T11:18:27.588000"
    },
    {
      "_id": "68763a93b007408b4f73c6ac",
      "booking_id": "bk68763a93b007408b4f73c6ab",
      "seat_id": "sg_hall2_A7",
      "status": "valid",
      "checkin_time": null,
      "checked_by": null,
      "barcode_data": "STHTTYA7220250715",
      "created_at": "2025-07-15T11:25:07.567000"
    },
    {
      "_id": "68763a93b007408b4f73c6ad",
      "booking_id": "bk68763a93b007408b4f73c6ab",
      "seat_id": "sg_hall2_A8",
      "status": "valid",
      "checkin_time": null,
      "checked_by": null,
      "barcode_data": "STHTTYA8220250715",
      "created_at": "2025-07-15T11:25:07.568000"
    },
    {
      "_id": "68763a93b007408b4f73c6ae",
      "booking_id": "bk68763a93b007408b4f73c6ab",
      "seat_id": "sg_hall2_A9",
      "status": "valid",
      "checkin_time": null,
      "checked_by": null,
      "barcode_data": "STHTTYA9220250715",
      "created_at": "2025-07-15T11:25:07.569000"
    },
    {
      "_id": "68763d146aa670e407a73091",
      "booking_id": "bk68763d146aa670e407a73090",
      "seat_id": "sg_hall2_B2",
      "status": "valid",
      "checkin_time": null,
      "checked_by": null,
      "barcode_data": "STHTTYB2220250715",
      "created_at": "2025-07-15T11:35:48.149000"
    },
    {
      "_id": "68763d146aa670e407a73092",
      "booking_id": "bk68763d146aa670e407a73090",
      "seat_id": "sg_hall2_B3",
      "status": "valid",
      "checkin_time": null,
      "checked_by": null,
      "barcode_data": "STHTTYB3220250715",
      "created_at": "2025-07-15T11:35:48.150000"
    },
    {
      "_id": "68763eef6aa670e407a73097",
      "booking_id": "bk68763eef6aa670e407a73096",
      "seat_id": "sg_hall2_B1",
      "status": "valid",
      "checkin_time": null,
      "checked_by": null,
      "barcode_data": "STHTTYB1220250715",
      "created_at": "2025-07-15T11:43:43.555000"
    },
    {
      "_id": "68763eef6aa670e407a73098",
      "booking_id": "bk68763eef6aa670e407a73096",
      "seat_id": "sg_hall2_B4",
      "status": "valid",
      "checkin_time": null,
      "checked_by": null,
      "barcode_data": "STHTTYB4220250715",
      "created_at": "2025-07-15T11:43:43.555000"
    },
    {
      "_id": "68763f4e63b7615f59fcbd87",
      "booking_id": "bk68763f4e63b7615f59fcbd86",
      "seat_id": "sg_hall2_B7",
      "status": "valid",
      "checkin_time": null,
      "checked_by": null,
      "barcode_data": "STHTTYB7220250715",
      "created_at": "2025-07-15T11:45:18.054000"
    },
    {
      "_id": "68763f4e63b7615f59fcbd88",
      "booking_id": "bk68763f4e63b7615f59fcbd86",
      "seat_id": "sg_hall2_B8",
      "status": "valid",
      "checkin_time": null,
      "checked_by": null,
      "barcode_data": "STHTTYB8220250715",
      "created_at": "2025-07-15T11:45:18.055000"
    },
    {
      "_id": "68763f6c1af7b1c67d579017",
      "booking_id": "bk68763f6c1af7b1c67d579016",
      "seat_id": "sg_hall2_A10",
      "status": "valid",
      "checkin_time": null,
      "checked_by": null,
      "barcode_data": "STHTTYA10220250715",
      "created_at": "2025-07-15T11:45:48.475000"
    },
    {
      "_id": "68763f6c1af7b1c67d579018",
      "booking_id": "bk68763f6c1af7b1c67d579016",
      "seat_id": "sg_hall2_B9",
      "status": "valid",
      "checkin_time": null,
      "checked_by": null,
      "barcode_data": "STHTTYB9220250715",
      "created_at": "2025-07-15T11:45:48.477000"
    },
    {
      "_id": "68763f6c1af7b1c67d579019",
      "booking_id": "bk68763f6c1af7b1c67d579016",
      "seat_id": "sg_hall2_B10",
      "status": "valid",
      "checkin_time": null,
      "checked_by": null,
      "barcode_data": "STHTTYB10220250715",
      "created_at": "2025-07-15T11:45:48.478000"
    },
    {
      "_id": "6876483dbc6a7b3c2dadf46a",
      "booking_id": "bk6876483dbc6a7b3c2dadf469",
      "seat_id": "sg_hall2_C1",
      "status": "valid",
      "checkin_time": null,
      "checked_by": null,
      "barcode_data": "STHTTYC1220250715",
      "created_at": "2025-07-15T12:23:25.232000"
    },
    {
      "_id": "6876483dbc6a7b3c2dadf46b",
      "booking_id": "bk6876483dbc6a7b3c2dadf469",
      "seat_id": "sg_hall2_C2",
      "status": "valid",
      "checkin_time": null,
      "checked_by": null,
      "barcode_data": "STHTTYC2220250715",
      "created_at": "2025-07-15T12:23:25.233000"
    },
    {
      "_id": "6876483dbc6a7b3c2dadf46c",
      "booking_id": "bk6876483dbc6a7b3c2dadf469",
      "seat_id": "sg_hall2_C3",
      "status": "valid",
      "checkin_time": null,
      "checked_by": null,
      "barcode_data": "STHTTYC3220250715",
      "created_at": "2025-07-15T12:23:25.233000"
    },
    {
      "_id": "68764856bc6a7b3c2dadf46f",
      "booking_id": "bk68764856bc6a7b3c2dadf46e",
      "seat_id": "sg_hall2_J3",
      "status": "valid",
      "checkin_time": null,
      "checked_by": null,
      "barcode_data": "STHTTYJ3220250715",
      "created_at": "2025-07-15T12:23:50.598000"
    },
    {
      "_id": "68764856bc6a7b3c2dadf470",
      "booking_id": "bk68764856bc6a7b3c2dadf46e",
      "seat_id": "sg_hall2_J4",
      "status": "valid",
      "checkin_time": null,
      "checked_by": null,
      "barcode_data": "STHTTYJ4220250715",
      "created_at": "2025-07-15T12:23:50.600000"
    },
    {
      "_id": "68764856bc6a7b3c2dadf471",
      "booking_id": "bk68764856bc6a7b3c2dadf46e",
      "seat_id": "sg_hall2_J5",
      "status": "valid",
      "checkin_time": null,
      "checked_by": null,
      "barcode_data": "STHTTYJ5220250715",
      "created_at": "2025-07-15T12:23:50.601000"
    },
    {
      "_id": "6876486bbc6a7b3c2dadf474",
      "booking_id": "bk6876486bbc6a7b3c2dadf473",
      "seat_id": "sg_hall3_J7",
      "status": "valid",
      "checkin_time": null,
      "checked_by": null,
      "barcode_data": "STHTTYJ7320250715",
      "created_at": "2025-07-15T12:24:11.332000"
    },
    {
      "_id": "6876486bbc6a7b3c2dadf475",
      "booking_id": "bk6876486bbc6a7b3c2dadf473",
      "seat_id": "sg_hall3_J8",
      "status": "valid",
      "checkin_time": null,
      "checked_by": null,
      "barcode_data": "STHTTYJ8320250715",
      "created_at": "2025-07-15T12:24:11.332000"
    },
    {
      "_id": "68764958509cbd1794f09dd0",
      "booking_id": "bk68764958509cbd1794f09dcf",
      "seat_id": "sg_hall2_C4",
      "status": "valid",
      "checkin_time": null,
      "checked_by": null,
      "barcode_data": "STHTTYC4220250715",
      "created_at": "2025-07-15T12:28:08.652000"
    },
    {
      "_id": "68764958509cbd1794f09dd1",
      "booking_id": "bk68764958509cbd1794f09dcf",
      "seat_id": "sg_hall2_C5",
      "status": "valid",
      "checkin_time": null,
      "checked_by": null,
      "barcode_data": "STHTTYC5220250715",
      "created_at": "2025-07-15T12:28:08.653000"
    },
    {
      "_id": "68764958509cbd1794f09dd2",
      "booking_id": "bk68764958509cbd1794f09dcf",
      "seat_id": "sg_hall2_C6",
      "status": "valid",
      "checkin_time": null,
      "checked_by": null,
      "barcode_data": "STHTTYC6220250715",
      "created_at": "2025-07-15T12:28:08.654000"
    },
    {
      "_id": "68764a0048e2fe54a4132763",
      "booking_id": "bk68764a0048e2fe54a4132762",
      "seat_id": "sg_hall2_C7",
      "status": "valid",
      "checkin_time": null,
      "checked_by": null,
      "barcode_data": "STHTTYC7220250715",
      "created_at": "2025-07-15T12:30:56.718000"
    },
    {
      "_id": "68764a0048e2fe54a4132764",
      "booking_id": "bk68764a0048e2fe54a4132762",
      "seat_id": "sg_hall2_C8",
      "status": "valid",
      "checkin_time": null,
      "checked_by": null,
      "barcode_data": "STHTTYC8220250715",
      "created_at": "2025-07-15T12:30:56.719000"
    },
    {
      "_id": "68764a0048e2fe54a4132765",
      "booking_id": "bk68764a0048e2fe54a4132762",
      "seat_id": "sg_hall2_C9",
      "status": "valid",
      "checkin_time": null,
      "checked_by": null,
      "barcode_data": "STHTTYC9220250715",
      "created_at": "2025-07-15T12:30:56.720000"
    },
    {
      "_id": "68764a0048e2fe54a4132766",
      "booking_id": "bk68764a0048e2fe54a4132762",
      "seat_id": "sg_hall2_C10",
      "status": "valid",
      "checkin_time": null,
      "checked_by": null,
      "barcode_data": "STHTTYC10220250715",
      "created_at": "2025-07-15T12:30:56.720000"
    },
    {
      "_id": "68764a9848e2fe54a4132769",
      "booking_id": "bk68764a9848e2fe54a4132768",
      "seat_id": "sg_hall2_D1",
      "status": "valid",
      "checkin_time": null,
      "checked_by": null,
      "barcode_data": "STHTTYD1220250715",
      "created_at": "2025-07-15T12:33:28.202000"
    },
    {
      "_id": "68764a9848e2fe54a413276a",
      "booking_id": "bk68764a9848e2fe54a4132768",
      "seat_id": "sg_hall2_D2",
      "status": "valid",
      "checkin_time": null,
      "checked_by": null,
      "barcode_data": "STHTTYD2220250715",
      "created_at": "2025-07-15T12:33:28.204000"
    },
    {
      "_id": "68764aa648e2fe54a413276d",
      "booking_id": "bk68764aa648e2fe54a413276c",
      "seat_id": "hn_hall1_A1",
      "status": "valid",
      "checkin_time": null,
      "checked_by": null,
      "barcode_data": "STM3GAA1120250715",
      "created_at": "2025-07-15T12:33:42.499000"
    },
    {
      "_id": "68764aa648e2fe54a413276e",
      "booking_id": "bk68764aa648e2fe54a413276c",
      "seat_id": "hn_hall1_A2",
      "status": "valid",
      "checkin_time": null,
      "checked_by": null,
      "barcode_data": "STM3GAA2120250715",
      "created_at": "2025-07-15T12:33:42.501000"
    },
    {
      "_id": "68764b2f184aa6d9529bae53",
      "booking_id": "bk68764b2f184aa6d9529bae52",
      "seat_id": "hn_hall1_A3",
      "status": "valid",
      "checkin_time": null,
      "checked_by": null,
      "barcode_data": "STM3GAA3120250715",
      "created_at": "2025-07-15T12:35:59.948000"
    },
    {
      "_id": "68764b2f184aa6d9529bae54",
      "booking_id": "bk68764b2f184aa6d9529bae52",
      "seat_id": "hn_hall1_A4",
      "status": "valid",
      "checkin_time": null,
      "checked_by": null,
      "barcode_data": "STM3GAA4120250715",
      "created_at": "2025-07-15T12:35:59.949000"
    },
    {
      "_id": "68764e25184aa6d9529bae57",
      "booking_id": "bk68764e25184aa6d9529bae56",
      "seat_id": "hn_hall3_A3",
      "status": "valid",
      "checkin_time": null,
      "checked_by": null,
      "barcode_data": "STELIOA3320250715",
      "created_at": "2025-07-15T12:48:37.553000"
    },
    {
      "_id": "68764e25184aa6d9529bae58",
      "booking_id": "bk68764e25184aa6d9529bae56",
      "seat_id": "hn_hall3_A4",
      "status": "valid",
      "checkin_time": null,
      "checked_by": null,
      "barcode_data": "STELIOA4320250715",
      "created_at": "2025-07-15T12:48:37.554000"
    },
    {
      "_id": "68764f5beb8d5b9d81c99599",
      "booking_id": "bk68764f5beb8d5b9d81c99598",
      "seat_id": "hn_hall3_A1",
      "status": "valid",
      "checkin_time": null,
      "checked_by": null,
      "barcode_data": "STELIOA1320250715",
      "created_at": "2025-07-15T12:53:47.275000"
    },
    {
      "_id": "687652d57deaaa8ebd7848e6",
      "booking_id": "bk687652d57deaaa8ebd7848e5",
      "seat_id": "hn_hall1_A4",
      "status": "valid",
      "checkin_time": null,
      "checked_by": null,
      "barcode_data": "STM3GAA4120250715",
      "created_at": "2025-07-15T13:08:37.936000"
    },
    {
      "_id": "687652d57deaaa8ebd7848e7",
      "booking_id": "bk687652d57deaaa8ebd7848e5",
      "seat_id": "hn_hall1_A5",
      "status": "valid",
      "checkin_time": null,
      "checked_by": null,
      "barcode_data": "STM3GAA5120250715",
      "created_at": "2025-07-15T13:08:37.937000"
    },
    {
      "_id": "687653b4f8faf0adcd3f0198",
      "booking_id": "bk687653b4f8faf0adcd3f0197",
      "seat_id": "hn_hall1_A5",
      "status": "valid",
      "checkin_time": null,
      "checked_by": null,
      "barcode_data": "STM3GAA5120250715",
      "created_at": "2025-07-15T13:12:20.306000"
    },
    {
      "_id": "687653b4f8faf0adcd3f0199",
      "booking_id": "bk687653b4f8faf0adcd3f0197",
      "seat_id": "hn_hall1_A6",
      "status": "valid",
      "checkin_time": null,
      "checked_by": null,
      "barcode_data": "STM3GAA6120250715",
      "created_at": "2025-07-15T13:12:20.308000"
    },
    {
      "_id": "6876559b0e7e254f305066ac",
      "booking_id": "bk6876559b0e7e254f305066ab",
      "seat_id": "sg_hall2_D3",
      "status": "valid",
      "checkin_time": null,
      "checked_by": null,
      "barcode_data": "STHTTYD3220250715",
      "created_at": "2025-07-15T13:20:27.845000"
    },
    {
      "_id": "6876559b0e7e254f305066ad",
      "booking_id": "bk6876559b0e7e254f305066ab",
      "seat_id": "sg_hall2_D4",
      "status": "valid",
      "checkin_time": null,
      "checked_by": null,
      "barcode_data": "STHTTYD4220250715",
      "created_at": "2025-07-15T13:20:27.846000"
    },
    {
      "_id": "68765a003384c32b4288b90a",
      "booking_id": "bk68765a003384c32b4288b909",
      "seat_id": "sg_hall2_D5",
      "status": "valid",
      "checkin_time": null,
      "checked_by": null,
      "barcode_data": "STHTTYD5220250715",
      "created_at": "2025-07-15T13:39:12.439000"
    },
    {
      "_id": "68765a003384c32b4288b90b",
      "booking_id": "bk68765a003384c32b4288b909",
      "seat_id": "sg_hall2_D6",
      "status": "valid",
      "checkin_time": null,
      "checked_by": null,
      "barcode_data": "STHTTYD6220250715",
      "created_at": "2025-07-15T13:39:12.440000"
    },
    {
      "_id": "687765e22b6de6c11f582df5",
      "booking_id": "bk687765e22b6de6c11f582df4",
      "seat_id": "sg_hall2_A4",
      "status": "valid",
      "checkin_time": null,
      "checked_by": null,
      "barcode_data": "STHTTYA4220250716",
      "created_at": "2025-07-16T08:42:10.247000"
    },
    {
      "_id": "687765e22b6de6c11f582df6",
      "booking_id": "bk687765e22b6de6c11f582df4",
      "seat_id": "sg_hall2_A5",
      "status": "valid",
      "checkin_time": null,
      "checked_by": null,
      "barcode_data": "STHTTYA5220250716",
      "created_at": "2025-07-16T08:42:10.249000"
    },
    {
      "_id": "687766d038f744b54135d5c0",
      "booking_id": "bk687766d038f744b54135d5bf",
      "seat_id": "sg_hall2_A6",
      "status": "valid",
      "checkin_time": null,
      "checked_by": null,
      "barcode_data": "STHTTYA6220250716",
      "created_at": "2025-07-16T08:46:08.611000"
    },
    {
      "_id": "687766d038f744b54135d5c1",
      "booking_id": "bk687766d038f744b54135d5bf",
      "seat_id": "sg_hall2_A7",
      "status": "valid",
      "checkin_time": null,
      "checked_by": null,
      "barcode_data": "STHTTYA7220250716",
      "created_at": "2025-07-16T08:46:08.612000"
    },
    {
      "_id": "6877670838f744b54135d5c4",
      "booking_id": "bk6877670838f744b54135d5c3",
      "seat_id": "hn_hall2_A4",
      "status": "valid",
      "checkin_time": null,
      "checked_by": null,
      "barcode_data": "STM3GAA4220250716",
      "created_at": "2025-07-16T08:47:04.234000"
    },
    {
      "_id": "6877670838f744b54135d5c5",
      "booking_id": "bk6877670838f744b54135d5c3",
      "seat_id": "hn_hall2_A5",
      "status": "valid",
      "checkin_time": null,
      "checked_by": null,
      "barcode_data": "STM3GAA5220250716",
      "created_at": "2025-07-16T08:47:04.236000"
    },
    {
      "_id": "6877683e38f744b54135d5c7",
      "booking_id": "bk6877683e38f744b54135d5c6",
      "seat_id": "sg_hall2_A8",
      "status": "valid",
      "checkin_time": null,
      "checked_by": null,
      "barcode_data": "STHTTYA8220250716",
      "created_at": "2025-07-16T08:52:14.413000"
    },
    {
      "_id": "6877683e38f744b54135d5c8",
      "booking_id": "bk6877683e38f744b54135d5c6",
      "seat_id": "sg_hall2_A9",
      "status": "valid",
      "checkin_time": null,
      "checked_by": null,
      "barcode_data": "STHTTYA9220250716",
      "created_at": "2025-07-16T08:52:14.414000"
    },
    {
      "_id": "6877685e38f744b54135d5cb",
      "booking_id": "bk6877685e38f744b54135d5ca",
      "seat_id": "sg_hall2_A10",
      "status": "valid",
      "checkin_time": null,
      "checked_by": null,
      "barcode_data": "STHTTYA10220250716",
      "created_at": "2025-07-16T08:52:46.379000"
    },
    {
      "_id": "687794ede448c62d3fb60a16",
      "booking_id": "bk687794ede448c62d3fb60a15",
      "seat_id": "sg_hall2_B8",
      "status": "valid",
      "checkin_time": null,
      "checked_by": null,
      "barcode_data": "STHTTYB8220250716",
      "created_at": "2025-07-16T12:02:53.430000"
    },
    {
      "_id": "687794ede448c62d3fb60a17",
      "booking_id": "bk687794ede448c62d3fb60a15",
      "seat_id": "sg_hall2_B9",
      "status": "valid",
      "checkin_time": null,
      "checked_by": null,
      "barcode_data": "STHTTYB9220250716",
      "created_at": "2025-07-16T12:02:53.431000"
    },
    {
      "_id": "68779532e448c62d3fb60a1a",
      "booking_id": "bk68779532e448c62d3fb60a19",
      "seat_id": "hn_hall1_A5",
      "status": "valid",
      "checkin_time": null,
      "checked_by": null,
      "barcode_data": "STHTTYA5120250717",
      "created_at": "2025-07-16T12:04:02.568000"
    },
    {
      "_id": "68779532e448c62d3fb60a1b",
      "booking_id": "bk68779532e448c62d3fb60a19",
      "seat_id": "hn_hall1_A6",
      "status": "valid",
      "checkin_time": null,
      "checked_by": null,
      "barcode_data": "STHTTYA6120250717",
      "created_at": "2025-07-16T12:04:02.569000"
    },
    {
      "_id": "687795cbe448c62d3fb60a1e",
      "booking_id": "bk687795cbe448c62d3fb60a1d",
      "seat_id": "hn_hall2_A6",
      "status": "valid",
      "checkin_time": null,
      "checked_by": null,
      "barcode_data": "STM3GAA6220250716",
      "created_at": "2025-07-16T12:06:35.240000"
    },
    {
      "_id": "687795cbe448c62d3fb60a1f",
      "booking_id": "bk687795cbe448c62d3fb60a1d",
      "seat_id": "hn_hall2_A7",
      "status": "valid",
      "checkin_time": null,
      "checked_by": null,
      "barcode_data": "STM3GAA7220250716",
      "created_at": "2025-07-16T12:06:35.241000"
    },
    {
      "_id": "687799e06f20f46eaa60c2d4",
      "booking_id": "bk687799e06f20f46eaa60c2d3",
      "seat_id": "hn_hall3_A9",
      "status": "valid",
      "checkin_time": null,
      "checked_by": null,
      "barcode_data": "STM3GAA9320250716",
      "created_at": "2025-07-16T12:24:00.442000"
    },
    {
      "_id": "687799e06f20f46eaa60c2d5",
      "booking_id": "bk687799e06f20f46eaa60c2d3",
      "seat_id": "hn_hall3_A10",
      "status": "valid",
      "checkin_time": null,
      "checked_by": null,
      "barcode_data": "STM3GAA10320250716",
      "created_at": "2025-07-16T12:24:00.443000"
    },
    {
      "_id": "68779ba86f20f46eaa60c2d7",
      "booking_id": "bk68779ba86f20f46eaa60c2d6",
      "seat_id": "hn_hall2_A8",
      "status": "valid",
      "checkin_time": null,
      "checked_by": null,
      "barcode_data": "STM3GAA8220250716",
      "created_at": "2025-07-16T12:31:36.547000"
    },
    {
      "_id": "68779ba86f20f46eaa60c2d8",
      "booking_id": "bk68779ba86f20f46eaa60c2d6",
      "seat_id": "hn_hall2_A9",
      "status": "valid",
      "checkin_time": null,
      "checked_by": null,
      "barcode_data": "STM3GAA9220250716",
      "created_at": "2025-07-16T12:31:36.548000"
    },
    {
      "_id": "68779ba86f20f46eaa60c2d9",
      "booking_id": "bk68779ba86f20f46eaa60c2d6",
      "seat_id": "hn_hall2_A10",
      "status": "valid",
      "checkin_time": null,
      "checked_by": null,
      "barcode_data": "STM3GAA10220250716",
      "created_at": "2025-07-16T12:31:36.549000"
    },
    {
      "_id": "6877c801e4396d3cb043a3b1",
      "booking_id": "bk6877c801e4396d3cb043a3b0",
      "seat_id": "sg_hall2_A3",
      "status": "valid",
      "checkin_time": null,
      "checked_by": null,
      "barcode_data": "STHTTYA3220250716",
      "created_at": "2025-07-16T15:40:49.998000"
    },
    {
      "_id": "687842484609340d88e97142",
      "booking_id": "bk687842484609340d88e97141",
      "seat_id": "hn_hall2_A7",
      "status": "valid",
      "checkin_time": null,
      "checked_by": null,
      "barcode_data": "STHTTYA7220250718",
      "created_at": "2025-07-17T00:22:32.206000"
    },
    {
      "_id": "687842484609340d88e97143",
      "booking_id": "bk687842484609340d88e97141",
      "seat_id": "hn_hall2_A8",
      "status": "valid",
      "checkin_time": null,
      "checked_by": null,
      "barcode_data": "STHTTYA8220250718",
      "created_at": "2025-07-17T00:22:32.207000"
    },
    {
      "_id": "6878429f4609340d88e97146",
      "booking_id": "bk6878429f4609340d88e97145",
      "seat_id": "hn_hall1_B4",
      "status": "valid",
      "checkin_time": null,
      "checked_by": null,
      "barcode_data": "STHTTYB4120250717",
      "created_at": "2025-07-17T00:23:59.332000"
    },
    {
      "_id": "6878429f4609340d88e97147",
      "booking_id": "bk6878429f4609340d88e97145",
      "seat_id": "hn_hall1_B5",
      "status": "valid",
      "checkin_time": null,
      "checked_by": null,
      "barcode_data": "STHTTYB5120250717",
      "created_at": "2025-07-17T00:23:59.333000"
    },
    {
      "_id": "687846f82bec96f509340be7",
      "booking_id": "bk687846f82bec96f509340be6",
      "seat_id": "hn_hall1_B6",
      "status": "valid",
      "checkin_time": null,
      "checked_by": null,
      "barcode_data": "STHTTYB6120250717",
      "created_at": "2025-07-17T00:42:32.164000"
    },
    {
      "_id": "687846f82bec96f509340be8",
      "booking_id": "bk687846f82bec96f509340be6",
      "seat_id": "hn_hall1_B7",
      "status": "valid",
      "checkin_time": null,
      "checked_by": null,
      "barcode_data": "STHTTYB7120250717",
      "created_at": "2025-07-17T00:42:32.166000"
    },
    {
      "_id": "6879b7b19bd77963eb6dd628",
      "booking_id": "bk6879b7b19bd77963eb6dd627",
      "seat_id": "hn_hall1_B8",
      "status": "valid",
      "checkin_time": null,
      "checked_by": null,
      "barcode_data": "STHTTYB8120250717",
      "created_at": "2025-07-18T02:55:45.257000"
    },
    {
      "_id": "6879b7b19bd77963eb6dd629",
      "booking_id": "bk6879b7b19bd77963eb6dd627",
      "seat_id": "hn_hall1_B9",
      "status": "valid",
      "checkin_time": null,
      "checked_by": null,
      "barcode_data": "STHTTYB9120250717",
      "created_at": "2025-07-18T02:55:45.259000"
    },
    {
      "_id": "687b919e38e885846992b0ed",
      "booking_id": "bk687b919e38e885846992b0ec",
      "seat_id": "sg_hall3_J9",
      "status": "valid",
      "checkin_time": null,
      "checked_by": null,
      "barcode_data": "STHTTYJ9320250720",
      "created_at": "2025-07-19T12:37:50.112000"
    },
    {
      "_id": "687b919e38e885846992b0ee",
      "booking_id": "bk687b919e38e885846992b0ec",
      "seat_id": "sg_hall3_J10",
      "status": "valid",
      "checkin_time": null,
      "checked_by": null,
      "barcode_data": "STHTTYJ10320250720",
      "created_at": "2025-07-19T12:37:50.113000"
    },
    {
      "_id": "687b92498f24a7d79dd34c94",
      "booking_id": "bk687b92498f24a7d79dd34c93",
      "seat_id": "hn_hall1_B8",
      "status": "valid",
      "checkin_time": null,
      "checked_by": null,
      "barcode_data": "STM3GAB8120250720",
      "created_at": "2025-07-19T12:40:41.284000"
    },
    {
      "_id": "687b92498f24a7d79dd34c95",
      "booking_id": "bk687b92498f24a7d79dd34c93",
      "seat_id": "hn_hall1_C7",
      "status": "valid",
      "checkin_time": null,
      "checked_by": null,
      "barcode_data": "STM3GAC7120250720",
      "created_at": "2025-07-19T12:40:41.285000"
    },
    {
      "_id": "687d8d8debc9c200c2425e4f",
      "booking_id": "bk687d8d8debc9c200c2425e4e",
      "seat_id": "hn_hall2_A6",
      "status": "valid",
      "checkin_time": null,
      "checked_by": null,
      "barcode_data": "STHTTYA6220250721",
      "created_at": "2025-07-21T00:45:01.358000"
    },
    {
      "_id": "687d8d8debc9c200c2425e50",
      "booking_id": "bk687d8d8debc9c200c2425e4e",
      "seat_id": "hn_hall2_A7",
      "status": "valid",
      "checkin_time": null,
      "checked_by": null,
      "barcode_data": "STHTTYA7220250721",
      "created_at": "2025-07-21T00:45:01.359000"
    },
    {
      "_id": "687d8db1ebc9c200c2425e53",
      "booking_id": "bk687d8db1ebc9c200c2425e52",
      "seat_id": "hn_hall2_B8",
      "status": "valid",
      "checkin_time": null,
      "checked_by": null,
      "barcode_data": "STHTTYB8220250721",
      "created_at": "2025-07-21T00:45:37.171000"
    },
    {
      "_id": "687d8dc5ebc9c200c2425e56",
      "booking_id": "bk687d8dc5ebc9c200c2425e55",
      "seat_id": "hn_hall2_B9",
      "status": "valid",
      "checkin_time": null,
      "checked_by": null,
      "barcode_data": "STHTTYB9220250721",
      "created_at": "2025-07-21T00:45:57.646000"
    },
    {
      "_id": "687f10443cf5c68937f009df",
      "booking_id": "bk687f10443cf5c68937f009de",
      "seat_id": "hn_hall1_A1",
      "status": "valid",
      "checkin_time": null,
      "checked_by": null,
      "barcode_data": "STM3GAA1120250722",
      "created_at": "2025-07-22T04:15:00.225000"
    },
    {
      "_id": "687f10443cf5c68937f009e0",
      "booking_id": "bk687f10443cf5c68937f009de",
      "seat_id": "hn_hall1_A2",
      "status": "valid",
      "checkin_time": null,
      "checked_by": null,
      "barcode_data": "STM3GAA2120250722",
      "created_at": "2025-07-22T04:15:00.227000"
    },
    {
      "_id": "687f10443cf5c68937f009e1",
      "booking_id": "bk687f10443cf5c68937f009de",
      "seat_id": "hn_hall1_A3",
      "status": "valid",
      "checkin_time": null,
      "checked_by": null,
      "barcode_data": "STM3GAA3120250722",
      "created_at": "2025-07-22T04:15:00.228000"
    },
    {
      "_id": "687f10443cf5c68937f009e2",
      "booking_id": "bk687f10443cf5c68937f009de",
      "seat_id": "hn_hall1_A4",
      "status": "valid",
      "checkin_time": null,
      "checked_by": null,
      "barcode_data": "STM3GAA4120250722",
      "created_at": "2025-07-22T04:15:00.230000"
    },
    {
      "_id": "687f105e3cf5c68937f009e5",
      "booking_id": "bk687f105e3cf5c68937f009e4",
      "seat_id": "sg_hall3_I3",
      "status": "valid",
      "checkin_time": null,
      "checked_by": null,
      "barcode_data": "STBIGDI3320250722",
      "created_at": "2025-07-22T04:15:26.727000"
    },
    {
      "_id": "687f105e3cf5c68937f009e6",
      "booking_id": "bk687f105e3cf5c68937f009e4",
      "seat_id": "sg_hall3_I4",
      "status": "valid",
      "checkin_time": null,
      "checked_by": null,
      "barcode_data": "STBIGDI4320250722",
      "created_at": "2025-07-22T04:15:26.728000"
    },
    {
      "_id": "687f105e3cf5c68937f009e7",
      "booking_id": "bk687f105e3cf5c68937f009e4",
      "seat_id": "sg_hall3_I5",
      "status": "valid",
      "checkin_time": null,
      "checked_by": null,
      "barcode_data": "STBIGDI5320250722",
      "created_at": "2025-07-22T04:15:26.729000"
    },
    {
      "_id": "687f105e3cf5c68937f009e8",
      "booking_id": "bk687f105e3cf5c68937f009e4",
      "seat_id": "sg_hall3_I6",
      "status": "valid",
      "checkin_time": null,
      "checked_by": null,
      "barcode_data": "STBIGDI6320250722",
      "created_at": "2025-07-22T04:15:26.730000"
    },
    {
      "_id": "687f10703cf5c68937f009eb",
      "booking_id": "bk687f10703cf5c68937f009ea",
      "seat_id": "hn_hall1_A1",
      "status": "valid",
      "checkin_time": null,
      "checked_by": null,
      "barcode_data": "STELIOA1120250722",
      "created_at": "2025-07-22T04:15:44.867000"
    },
    {
      "_id": "687f10703cf5c68937f009ec",
      "booking_id": "bk687f10703cf5c68937f009ea",
      "seat_id": "hn_hall1_A2",
      "status": "valid",
      "checkin_time": null,
      "checked_by": null,
      "barcode_data": "STELIOA2120250722",
      "created_at": "2025-07-22T04:15:44.868000"
    },
    {
      "_id": "687f10703cf5c68937f009ed",
      "booking_id": "bk687f10703cf5c68937f009ea",
      "seat_id": "hn_hall1_A3",
      "status": "valid",
      "checkin_time": null,
      "checked_by": null,
      "barcode_data": "STELIOA3120250722",
      "created_at": "2025-07-22T04:15:44.869000"
    },
    {
      "_id": "687f10703cf5c68937f009ee",
      "booking_id": "bk687f10703cf5c68937f009ea",
      "seat_id": "hn_hall1_A4",
      "status": "valid",
      "checkin_time": null,
      "checked_by": null,
      "barcode_data": "STELIOA4120250722",
      "created_at": "2025-07-22T04:15:44.869000"
    },
    {
      "_id": "687f10703cf5c68937f009ef",
      "booking_id": "bk687f10703cf5c68937f009ea",
      "seat_id": "hn_hall1_A5",
      "status": "valid",
      "checkin_time": null,
      "checked_by": null,
      "barcode_data": "STELIOA5120250722",
      "created_at": "2025-07-22T04:15:44.870000"
    },
    {
      "_id": "687f107f3cf5c68937f009f2",
      "booking_id": "bk687f107f3cf5c68937f009f1",
      "seat_id": "hn_hall2_A1",
      "status": "valid",
      "checkin_time": null,
      "checked_by": null,
      "barcode_data": "STMAKHA1220250722",
      "created_at": "2025-07-22T04:15:59.561000"
    },
    {
      "_id": "687f107f3cf5c68937f009f3",
      "booking_id": "bk687f107f3cf5c68937f009f1",
      "seat_id": "hn_hall2_A2",
      "status": "valid",
      "checkin_time": null,
      "checked_by": null,
      "barcode_data": "STMAKHA2220250722",
      "created_at": "2025-07-22T04:15:59.562000"
    },
    {
      "_id": "687f107f3cf5c68937f009f4",
      "booking_id": "bk687f107f3cf5c68937f009f1",
      "seat_id": "hn_hall2_A3",
      "status": "valid",
      "checkin_time": null,
      "checked_by": null,
      "barcode_data": "STMAKHA3220250722",
      "created_at": "2025-07-22T04:15:59.563000"
    },
    {
      "_id": "687f107f3cf5c68937f009f5",
      "booking_id": "bk687f107f3cf5c68937f009f1",
      "seat_id": "hn_hall2_A4",
      "status": "valid",
      "checkin_time": null,
      "checked_by": null,
      "barcode_data": "STMAKHA4220250722",
      "created_at": "2025-07-22T04:15:59.564000"
    },
    {
      "_id": "687f10903cf5c68937f009f8",
      "booking_id": "bk687f10903cf5c68937f009f7",
      "seat_id": "sg_hall1_B3",
      "status": "valid",
      "checkin_time": null,
      "checked_by": null,
      "barcode_data": "STBIGDB3120250722",
      "created_at": "2025-07-22T04:16:16.640000"
    },
    {
      "_id": "687f10903cf5c68937f009f9",
      "booking_id": "bk687f10903cf5c68937f009f7",
      "seat_id": "sg_hall1_B4",
      "status": "valid",
      "checkin_time": null,
      "checked_by": null,
      "barcode_data": "STBIGDB4120250722",
      "created_at": "2025-07-22T04:16:16.641000"
    },
    {
      "_id": "687f10903cf5c68937f009fa",
      "booking_id": "bk687f10903cf5c68937f009f7",
      "seat_id": "sg_hall1_B5",
      "status": "valid",
      "checkin_time": null,
      "checked_by": null,
      "barcode_data": "STBIGDB5120250722",
      "created_at": "2025-07-22T04:16:16.641000"
    },
    {
      "_id": "687f10903cf5c68937f009fb",
      "booking_id": "bk687f10903cf5c68937f009f7",
      "seat_id": "sg_hall1_B6",
      "status": "valid",
      "checkin_time": null,
      "checked_by": null,
      "barcode_data": "STBIGDB6120250722",
      "created_at": "2025-07-22T04:16:16.642000"
    },
    {
      "_id": "687f10a03cf5c68937f009fe",
      "booking_id": "bk687f10a03cf5c68937f009fd",
      "seat_id": "hn_hall1_A1",
      "status": "valid",
      "checkin_time": null,
      "checked_by": null,
      "barcode_data": "ST28YEA1120250722",
      "created_at": "2025-07-22T04:16:32.560000"
    },
    {
      "_id": "687f10a03cf5c68937f009ff",
      "booking_id": "bk687f10a03cf5c68937f009fd",
      "seat_id": "hn_hall1_A2",
      "status": "valid",
      "checkin_time": null,
      "checked_by": null,
      "barcode_data": "ST28YEA2120250722",
      "created_at": "2025-07-22T04:16:32.561000"
    },
    {
      "_id": "687f10a03cf5c68937f00a00",
      "booking_id": "bk687f10a03cf5c68937f009fd",
      "seat_id": "hn_hall1_A3",
      "status": "valid",
      "checkin_time": null,
      "checked_by": null,
      "barcode_data": "ST28YEA3120250722",
      "created_at": "2025-07-22T04:16:32.562000"
    },
    {
      "_id": "687f10a03cf5c68937f00a01",
      "booking_id": "bk687f10a03cf5c68937f009fd",
      "seat_id": "hn_hall1_A4",
      "status": "valid",
      "checkin_time": null,
      "checked_by": null,
      "barcode_data": "ST28YEA4120250722",
      "created_at": "2025-07-22T04:16:32.562000"
    },
    {
      "_id": "687f10a03cf5c68937f00a02",
      "booking_id": "bk687f10a03cf5c68937f009fd",
      "seat_id": "hn_hall1_A5",
      "status": "valid",
      "checkin_time": null,
      "checked_by": null,
      "barcode_data": "ST28YEA5120250722",
      "created_at": "2025-07-22T04:16:32.563000"
    },
    {
      "_id": "687f10b13cf5c68937f00a05",
      "booking_id": "bk687f10b13cf5c68937f00a04",
      "seat_id": "hn_hall2_B6",
      "status": "valid",
      "checkin_time": null,
      "checked_by": null,
      "barcode_data": "STMAKHB6220250722",
      "created_at": "2025-07-22T04:16:49.005000"
    },
    {
      "_id": "687f10b13cf5c68937f00a06",
      "booking_id": "bk687f10b13cf5c68937f00a04",
      "seat_id": "hn_hall2_B7",
      "status": "valid",
      "checkin_time": null,
      "checked_by": null,
      "barcode_data": "STMAKHB7220250722",
      "created_at": "2025-07-22T04:16:49.006000"
    },
    {
      "_id": "687f10b13cf5c68937f00a07",
      "booking_id": "bk687f10b13cf5c68937f00a04",
      "seat_id": "hn_hall2_B8",
      "status": "valid",
      "checkin_time": null,
      "checked_by": null,
      "barcode_data": "STMAKHB8220250722",
      "created_at": "2025-07-22T04:16:49.007000"
    },
    {
      "_id": "687f10b13cf5c68937f00a08",
      "booking_id": "bk687f10b13cf5c68937f00a04",
      "seat_id": "hn_hall2_B9",
      "status": "valid",
      "checkin_time": null,
      "checked_by": null,
      "barcode_data": "STMAKHB9220250722",
      "created_at": "2025-07-22T04:16:49.008000"
    },
    {
      "_id": "687f10bd3cf5c68937f00a0b",
      "booking_id": "bk687f10bd3cf5c68937f00a0a",
      "seat_id": "sg_hall1_A1",
      "status": "valid",
      "checkin_time": null,
      "checked_by": null,
      "barcode_data": "STMAKHA1120250722",
      "created_at": "2025-07-22T04:17:01.589000"
    },
    {
      "_id": "687f10bd3cf5c68937f00a0c",
      "booking_id": "bk687f10bd3cf5c68937f00a0a",
      "seat_id": "sg_hall1_A2",
      "status": "valid",
      "checkin_time": null,
      "checked_by": null,
      "barcode_data": "STMAKHA2120250722",
      "created_at": "2025-07-22T04:17:01.590000"
    },
    {
      "_id": "687f10bd3cf5c68937f00a0d",
      "booking_id": "bk687f10bd3cf5c68937f00a0a",
      "seat_id": "sg_hall1_A3",
      "status": "valid",
      "checkin_time": null,
      "checked_by": null,
      "barcode_data": "STMAKHA3120250722",
      "created_at": "2025-07-22T04:17:01.591000"
    },
    {
      "_id": "687f10bd3cf5c68937f00a0e",
      "booking_id": "bk687f10bd3cf5c68937f00a0a",
      "seat_id": "sg_hall1_B3",
      "status": "valid",
      "checkin_time": null,
      "checked_by": null,
      "barcode_data": "STMAKHB3120250722",
      "created_at": "2025-07-22T04:17:01.591000"
    },
    {
      "_id": "687f10d23cf5c68937f00a11",
      "booking_id": "bk687f10d23cf5c68937f00a10",
      "seat_id": "sg_hall2_G1",
      "status": "valid",
      "checkin_time": null,
      "checked_by": null,
      "barcode_data": "STMAKHG1220250722",
      "created_at": "2025-07-22T04:17:22.951000"
    },
    {
      "_id": "687f10d23cf5c68937f00a12",
      "booking_id": "bk687f10d23cf5c68937f00a10",
      "seat_id": "sg_hall2_G2",
      "status": "valid",
      "checkin_time": null,
      "checked_by": null,
      "barcode_data": "STMAKHG2220250722",
      "created_at": "2025-07-22T04:17:22.952000"
    },
    {
      "_id": "687f10d23cf5c68937f00a13",
      "booking_id": "bk687f10d23cf5c68937f00a10",
      "seat_id": "sg_hall2_G3",
      "status": "valid",
      "checkin_time": null,
      "checked_by": null,
      "barcode_data": "STMAKHG3220250722",
      "created_at": "2025-07-22T04:17:22.953000"
    },
    {
      "_id": "687f10d23cf5c68937f00a14",
      "booking_id": "bk687f10d23cf5c68937f00a10",
      "seat_id": "sg_hall2_G4",
      "status": "valid",
      "checkin_time": null,
      "checked_by": null,
      "barcode_data": "STMAKHG4220250722",
      "created_at": "2025-07-22T04:17:22.954000"
    },
    {
      "_id": "687f10d23cf5c68937f00a15",
      "booking_id": "bk687f10d23cf5c68937f00a10",
      "seat_id": "sg_hall2_G5",
      "status": "valid",
      "checkin_time": null,
      "checked_by": null,
      "barcode_data": "STMAKHG5220250722",
      "created_at": "2025-07-22T04:17:22.954000"
    },
    {
      "_id": "687f10d23cf5c68937f00a16",
      "booking_id": "bk687f10d23cf5c68937f00a10",
      "seat_id": "sg_hall2_G6",
      "status": "valid",
      "checkin_time": null,
      "checked_by": null,
      "barcode_data": "STMAKHG6220250722",
      "created_at": "2025-07-22T04:17:22.955000"
    },
    {
      "_id": "687f10d23cf5c68937f00a17",
      "booking_id": "bk687f10d23cf5c68937f00a10",
      "seat_id": "sg_hall2_G7",
      "status": "valid",
      "checkin_time": null,
      "checked_by": null,
      "barcode_data": "STMAKHG7220250722",
      "created_at": "2025-07-22T04:17:22.956000"
    },
    {
      "_id": "687f10d23cf5c68937f00a18",
      "booking_id": "bk687f10d23cf5c68937f00a10",
      "seat_id": "sg_hall2_G8",
      "status": "valid",
      "checkin_time": null,
      "checked_by": null,
      "barcode_data": "STMAKHG8220250722",
      "created_at": "2025-07-22T04:17:22.957000"
    },
    {
      "_id": "687f10d23cf5c68937f00a19",
      "booking_id": "bk687f10d23cf5c68937f00a10",
      "seat_id": "sg_hall2_G9",
      "status": "valid",
      "checkin_time": null,
      "checked_by": null,
      "barcode_data": "STMAKHG9220250722",
      "created_at": "2025-07-22T04:17:22.958000"
    },
    {
      "_id": "687f10d23cf5c68937f00a1a",
      "booking_id": "bk687f10d23cf5c68937f00a10",
      "seat_id": "sg_hall2_G10",
      "status": "valid",
      "checkin_time": null,
      "checked_by": null,
      "barcode_data": "STMAKHG10220250722",
      "created_at": "2025-07-22T04:17:22.959000"
    },
    {
      "_id": "687f10e63cf5c68937f00a1d",
      "booking_id": "bk687f10e63cf5c68937f00a1c",
      "seat_id": "sg_hall2_B1",
      "status": "checked_in",
      "checkin_time": null,
      "checked_by": null,
      "barcode_data": "STELIOB1220250722",
      "created_at": "2025-07-22T04:17:42.211000",
      "checked_in_at": "2025-07-29T19:13:37.858000",
      "checked_in_by": "staff"
    },
    {
      "_id": "687f10e63cf5c68937f00a1e",
      "booking_id": "bk687f10e63cf5c68937f00a1c",
      "seat_id": "sg_hall2_B2",
      "status": "checked_in",
      "checkin_time": null,
      "checked_by": null,
      "barcode_data": "STELIOB2220250722",
      "created_at": "2025-07-22T04:17:42.212000",
      "checked_in_at": "2025-07-29T19:16:31.583000",
      "checked_in_by": "test"
    },
    {
      "_id": "687f10e63cf5c68937f00a1f",
      "booking_id": "bk687f10e63cf5c68937f00a1c",
      "seat_id": "sg_hall2_B3",
      "status": "checked_in",
      "checkin_time": null,
      "checked_by": null,
      "barcode_data": "STELIOB3220250722",
      "created_at": "2025-07-22T04:17:42.214000",
      "checked_in_at": "2025-07-29T19:17:16.432000",
      "checked_in_by": "staff"
    },
    {
      "_id": "687f10e63cf5c68937f00a20",
      "booking_id": "bk687f10e63cf5c68937f00a1c",
      "seat_id": "sg_hall2_B4",
      "status": "checked_in",
      "checkin_time": null,
      "checked_by": null,
      "barcode_data": "STELIOB4220250722",
      "created_at": "2025-07-22T04:17:42.215000",
      "checked_in_at": "2025-07-29T19:17:25.033000",
      "checked_in_by": "staff"
    },
    {
      "_id": "687f10e63cf5c68937f00a21",
      "booking_id": "bk687f10e63cf5c68937f00a1c",
      "seat_id": "sg_hall2_B5",
      "status": "checked_in",
      "checkin_time": null,
      "checked_by": null,
      "barcode_data": "STELIOB5220250722",
      "created_at": "2025-07-22T04:17:42.216000",
      "checked_in_at": "2025-07-29T19:17:25.034000",
      "checked_in_by": "staff"
    },
    {
      "_id": "687f10e63cf5c68937f00a22",
      "booking_id": "bk687f10e63cf5c68937f00a1c",
      "seat_id": "sg_hall2_B6",
      "status": "checked_in",
      "checkin_time": null,
      "checked_by": null,
      "barcode_data": "STELIOB6220250722",
      "created_at": "2025-07-22T04:17:42.218000",
      "checked_in_at": "2025-07-29T19:58:40.581000",
      "checked_in_by": "staff"
    },
    {
      "_id": "687f10e63cf5c68937f00a23",
      "booking_id": "bk687f10e63cf5c68937f00a1c",
      "seat_id": "sg_hall2_B7",
      "status": "checked_in",
      "checkin_time": null,
      "checked_by": null,
      "barcode_data": "STELIOB7220250722",
      "created_at": "2025-07-22T04:17:42.219000",
      "checked_in_at": "2025-07-29T20:03:21.728000",
      "checked_in_by": "staff"
    },
    {
      "_id": "687f10e63cf5c68937f00a24",
      "booking_id": "bk687f10e63cf5c68937f00a1c",
      "seat_id": "sg_hall2_B8",
      "status": "checked_in",
      "checkin_time": null,
      "checked_by": null,
      "barcode_data": "STELIOB8220250722",
      "created_at": "2025-07-22T04:17:42.220000",
      "checked_in_at": "2025-07-29T20:03:21.730000",
      "checked_in_by": "staff"
    },
    {
      "_id": "687f10e63cf5c68937f00a25",
      "booking_id": "bk687f10e63cf5c68937f00a1c",
      "seat_id": "sg_hall2_B9",
      "status": "checked_in",
      "checkin_time": null,
      "checked_by": null,
      "barcode_data": "STELIOB9220250722",
      "created_at": "2025-07-22T04:17:42.222000",
      "checked_in_at": "2025-07-29T20:05:49.186000",
      "checked_in_by": "staff"
    },
    {
      "_id": "687f10e63cf5c68937f00a26",
      "booking_id": "bk687f10e63cf5c68937f00a1c",
      "seat_id": "sg_hall2_B10",
      "status": "valid",
      "checkin_time": null,
      "checked_by": null,
      "barcode_data": "STELIOB10220250722",
      "created_at": "2025-07-22T04:17:42.223000"
    },
    {
      "_id": "687fa75460708e7b6dd6dd86",
      "booking_id": "bk687fa75460708e7b6dd6dd85",
      "seat_id": "hn_hall3_A3",
      "status": "checked_in",
      "checkin_time": null,
      "checked_by": null,
      "barcode_data": "STM3GAA3320250723",
      "created_at": "2025-07-22T14:59:32.849000",
      "checked_in_at": "2025-07-29T19:48:25.639000",
      "checked_in_by": "staff"
    },
    {
      "_id": "687fa75460708e7b6dd6dd87",
      "booking_id": "bk687fa75460708e7b6dd6dd85",
      "seat_id": "hn_hall3_A4",
      "status": "checked_in",
      "checkin_time": null,
      "checked_by": null,
      "barcode_data": "STM3GAA4320250723",
      "created_at": "2025-07-22T14:59:32.850000",
      "checked_in_at": "2025-07-29T19:48:25.640000",
      "checked_in_by": "staff"
    },
    {
      "_id": "68888acb8297d0fea338672a",
      "booking_id": "bk68888acb8297d0fea3386729",
      "seat_id": "hn_hall3_A6",
      "status": "checked_in",
      "checkin_time": null,
      "checked_by": null,
      "barcode_data": "STHTTYA6320250729",
      "created_at": "2025-07-29T08:48:11.451000",
      "checked_in_at": "2025-07-29T19:41:25.608000",
      "checked_in_by": "staff"
    },
    {
      "_id": "68888acb8297d0fea338672b",
      "booking_id": "bk68888acb8297d0fea3386729",
      "seat_id": "hn_hall3_A7",
      "status": "checked_in",
      "checkin_time": null,
      "checked_by": null,
      "barcode_data": "STHTTYA7320250729",
      "created_at": "2025-07-29T08:48:11.452000",
      "checked_in_at": "2025-07-29T19:40:43.565000",
      "checked_in_by": "staff"
    },
    {
      "_id": "ticket_test_1",
      "booking_id": "test_booking_1",
      "seat_id": "hn_hall1_A1",
      "status": "valid",
      "barcode_data": "STELIOB9220250722_T1",
      "created_at": "2025-07-29T20:11:49.806000"
    },
    {
      "_id": "ticket_test_2",
      "booking_id": "test_booking_1",
      "seat_id": "hn_hall1_A2",
      "status": "checked_in",
      "barcode_data": "STELIOB9220250722_T2",
      "created_at": "2025-07-29T20:11:49.806000"
    },
    {
      "_id": "6888d0e0ee5fac3d4c61a692",
      "booking_id": "bk6888d0e0ee5fac3d4c61a690",
      "seat_id": "hn_hall3_A5",
      "status": "valid",
      "checkin_time": null,
      "checked_by": null,
      "barcode_data": "STHTTYA5320250729",
      "created_at": "2025-07-29T13:47:12.307000"
    },
    {
      "_id": "6888d0e0ee5fac3d4c61a693",
      "booking_id": "bk6888d0e0ee5fac3d4c61a690",
      "seat_id": "hn_hall3_A6",
      "status": "valid",
      "checkin_time": null,
      "checked_by": null,
      "barcode_data": "STHTTYA6320250729",
      "created_at": "2025-07-29T13:47:12.308000"
    },
    {
      "_id": "6888d107ee5fac3d4c61a698",
      "booking_id": "bk6888d107ee5fac3d4c61a696",
      "seat_id": "sg_hall1_A7",
      "status": "valid",
      "checkin_time": null,
      "checked_by": null,
      "barcode_data": "STM3GAA7120250730",
      "created_at": "2025-07-29T13:47:51.233000"
    },
    {
      "_id": "6888d107ee5fac3d4c61a699",
      "booking_id": "bk6888d107ee5fac3d4c61a696",
      "seat_id": "sg_hall1_A8",
      "status": "valid",
      "checkin_time": null,
      "checked_by": null,
      "barcode_data": "STM3GAA8120250730",
      "created_at": "2025-07-29T13:47:51.233000"
    },
    {
      "_id": "6888d125ee5fac3d4c61a69e",
      "booking_id": "bk6888d125ee5fac3d4c61a69c",
      "seat_id": "hn_hall1_A1",
      "status": "checked_in",
      "checkin_time": null,
      "checked_by": null,
      "barcode_data": "STELIOA1120250729",
      "created_at": "2025-07-29T13:48:21.561000",
      "checked_in_at": "2025-07-29T21:40:27.730000",
      "checked_in_by": "staff"
    },
    {
      "_id": "6888d125ee5fac3d4c61a69f",
      "booking_id": "bk6888d125ee5fac3d4c61a69c",
      "seat_id": "hn_hall1_A2",
      "status": "checked_in",
      "checkin_time": null,
      "checked_by": null,
      "barcode_data": "STELIOA2120250729",
      "created_at": "2025-07-29T13:48:21.563000",
      "checked_in_at": "2025-07-29T21:40:27.737000",
      "checked_in_by": "staff"
    },
    {
      "_id": "6888d125ee5fac3d4c61a6a0",
      "booking_id": "bk6888d125ee5fac3d4c61a69c",
      "seat_id": "hn_hall1_A3",
      "status": "valid",
      "checkin_time": null,
      "checked_by": null,
      "barcode_data": "STELIOA3120250729",
      "created_at": "2025-07-29T13:48:21.563000"
    },
    {
      "_id": "6888d125ee5fac3d4c61a6a1",
      "booking_id": "bk6888d125ee5fac3d4c61a69c",
      "seat_id": "hn_hall1_A4",
      "status": "valid",
      "checkin_time": null,
      "checked_by": null,
      "barcode_data": "STELIOA4120250729",
      "created_at": "2025-07-29T13:48:21.564000"
    },
    {
      "_id": "6888d125ee5fac3d4c61a6a2",
      "booking_id": "bk6888d125ee5fac3d4c61a69c",
      "seat_id": "hn_hall1_A5",
      "status": "valid",
      "checkin_time": null,
      "checked_by": null,
      "barcode_data": "STELIOA5120250729",
      "created_at": "2025-07-29T13:48:21.566000"
    },
    {
      "_id": "6888d125ee5fac3d4c61a6a3",
      "booking_id": "bk6888d125ee5fac3d4c61a69c",
      "seat_id": "hn_hall1_A6",
      "status": "valid",
      "checkin_time": null,
      "checked_by": null,
      "barcode_data": "STELIOA6120250729",
      "created_at": "2025-07-29T13:48:21.567000"
    },
    {
      "_id": "6888d125ee5fac3d4c61a6a4",
      "booking_id": "bk6888d125ee5fac3d4c61a69c",
      "seat_id": "hn_hall1_A7",
      "status": "valid",
      "checkin_time": null,
      "checked_by": null,
      "barcode_data": "STELIOA7120250729",
      "created_at": "2025-07-29T13:48:21.569000"
    },
    {
      "_id": "6888d125ee5fac3d4c61a6a5",
      "booking_id": "bk6888d125ee5fac3d4c61a69c",
      "seat_id": "hn_hall1_A8",
      "status": "valid",
      "checkin_time": null,
      "checked_by": null,
      "barcode_data": "STELIOA8120250729",
      "created_at": "2025-07-29T13:48:21.571000"
    },
    {
      "_id": "6888d125ee5fac3d4c61a6a6",
      "booking_id": "bk6888d125ee5fac3d4c61a69c",
      "seat_id": "hn_hall1_A9",
      "status": "valid",
      "checkin_time": null,
      "checked_by": null,
      "barcode_data": "STELIOA9120250729",
      "created_at": "2025-07-29T13:48:21.572000"
    },
    {
      "_id": "6888d125ee5fac3d4c61a6a7",
      "booking_id": "bk6888d125ee5fac3d4c61a69c",
      "seat_id": "hn_hall1_A10",
      "status": "checked_in",
      "checkin_time": null,
      "checked_by": null,
      "barcode_data": "STELIOA10120250729",
      "created_at": "2025-07-29T13:48:21.573000",
      "checked_in_at": "2025-07-29T21:18:55.292000",
      "checked_in_by": "staff"
    },
    {
      "_id": "68892a604e55324d0e1a88f9",
      "booking_id": "bk68892a604e55324d0e1a88f7",
      "seat_id": "sg_hall1_B7",
      "status": "valid",
      "checkin_time": null,
      "checked_by": null,
      "barcode_data": "STM3GAB7120250730",
      "created_at": "2025-07-29T20:09:04.444000"
    },
    {
      "_id": "68892a604e55324d0e1a88fa",
      "booking_id": "bk68892a604e55324d0e1a88f7",
      "seat_id": "sg_hall1_B8",
      "status": "valid",
      "checkin_time": null,
      "checked_by": null,
      "barcode_data": "STM3GAB8120250730",
      "created_at": "2025-07-29T20:09:04.445000"
    },
    {
      "_id": "68892a604e55324d0e1a88fb",
      "booking_id": "bk68892a604e55324d0e1a88f7",
      "seat_id": "sg_hall1_B9",
      "status": "valid",
      "checkin_time": null,
      "checked_by": null,
      "barcode_data": "STM3GAB9120250730",
      "created_at": "2025-07-29T20:09:04.447000"
    },
    {
      "_id": "68892a604e55324d0e1a88fc",
      "booking_id": "bk68892a604e55324d0e1a88f7",
      "seat_id": "sg_hall1_B10",
      "status": "valid",
      "checkin_time": null,
      "checked_by": null,
      "barcode_data": "STM3GAB10120250730",
      "created_at": "2025-07-29T20:09:04.448000"
    },
    {
      "_id": "68892a8b4e55324d0e1a8902",
      "booking_id": "bk68892a8b4e55324d0e1a8900",
      "seat_id": "hn_hall2_A3",
      "status": "valid",
      "checkin_time": null,
      "checked_by": null,
      "barcode_data": "STBIGDA3220250730",
      "created_at": "2025-07-29T20:09:47.931000"
    },
    {
      "_id": "68892a8b4e55324d0e1a8903",
      "booking_id": "bk68892a8b4e55324d0e1a8900",
      "seat_id": "hn_hall2_A4",
      "status": "valid",
      "checkin_time": null,
      "checked_by": null,
      "barcode_data": "STBIGDA4220250730",
      "created_at": "2025-07-29T20:09:47.932000"
    },
    {
      "_id": "68892a8b4e55324d0e1a8904",
      "booking_id": "bk68892a8b4e55324d0e1a8900",
      "seat_id": "hn_hall2_A5",
      "status": "valid",
      "checkin_time": null,
      "checked_by": null,
      "barcode_data": "STBIGDA5220250730",
      "created_at": "2025-07-29T20:09:47.933000"
    },
    {
      "_id": "68892a8b4e55324d0e1a8905",
      "booking_id": "bk68892a8b4e55324d0e1a8900",
      "seat_id": "hn_hall2_A6",
      "status": "valid",
      "checkin_time": null,
      "checked_by": null,
      "barcode_data": "STBIGDA6220250730",
      "created_at": "2025-07-29T20:09:47.934000"
    },
    {
      "_id": "68892a8b4e55324d0e1a8906",
      "booking_id": "bk68892a8b4e55324d0e1a8900",
      "seat_id": "hn_hall2_B3",
      "status": "valid",
      "checkin_time": null,
      "checked_by": null,
      "barcode_data": "STBIGDB3220250730",
      "created_at": "2025-07-29T20:09:47.935000"
    },
    {
      "_id": "68892a8b4e55324d0e1a8907",
      "booking_id": "bk68892a8b4e55324d0e1a8900",
      "seat_id": "hn_hall2_B4",
      "status": "valid",
      "checkin_time": null,
      "checked_by": null,
      "barcode_data": "STBIGDB4220250730",
      "created_at": "2025-07-29T20:09:47.936000"
    },
    {
      "_id": "68892a8b4e55324d0e1a8908",
      "booking_id": "bk68892a8b4e55324d0e1a8900",
      "seat_id": "hn_hall2_B5",
      "status": "valid",
      "checkin_time": null,
      "checked_by": null,
      "barcode_data": "STBIGDB5220250730",
      "created_at": "2025-07-29T20:09:47.937000"
    },
    {
      "_id": "68892a8b4e55324d0e1a8909",
      "booking_id": "bk68892a8b4e55324d0e1a8900",
      "seat_id": "hn_hall2_B6",
      "status": "valid",
      "checkin_time": null,
      "checked_by": null,
      "barcode_data": "STBIGDB6220250730",
      "created_at": "2025-07-29T20:09:47.938000"
    },
    {
      "_id": "688990a02147c4510bce5aa5",
      "booking_id": "bk688990a02147c4510bce5aa3",
      "seat_id": "sg_hall1_A6",
      "status": "valid",
      "checkin_time": null,
      "checked_by": null,
      "barcode_data": "STM3GAA6120250730",
      "created_at": "2025-07-30T03:25:20.480000"
    },
    {
      "_id": "688990a02147c4510bce5aa6",
      "booking_id": "bk688990a02147c4510bce5aa3",
      "seat_id": "sg_hall1_A7",
      "status": "valid",
      "checkin_time": null,
      "checked_by": null,
      "barcode_data": "STM3GAA7120250730",
      "created_at": "2025-07-30T03:25:20.481000"
    },
    {
      "_id": "688990a02147c4510bce5aa7",
      "booking_id": "bk688990a02147c4510bce5aa3",
      "seat_id": "sg_hall1_A8",
      "status": "valid",
      "checkin_time": null,
      "checked_by": null,
      "barcode_data": "STM3GAA8120250730",
      "created_at": "2025-07-30T03:25:20.482000"
    },
    {
      "_id": "688990a02147c4510bce5aa8",
      "booking_id": "bk688990a02147c4510bce5aa3",
      "seat_id": "sg_hall1_B6",
      "status": "valid",
      "checkin_time": null,
      "checked_by": null,
      "barcode_data": "STM3GAB6120250730",
      "created_at": "2025-07-30T03:25:20.482000"
    },
    {
      "_id": "688990a02147c4510bce5aa9",
      "booking_id": "bk688990a02147c4510bce5aa3",
      "seat_id": "sg_hall1_B7",
      "status": "valid",
      "checkin_time": null,
      "checked_by": null,
      "barcode_data": "STM3GAB7120250730",
      "created_at": "2025-07-30T03:25:20.483000"
    }
  ]
}